setup.py
derrick/__init__.py
derrick/resource.py
derrick.egg-info/PKG-INFO
derrick.egg-info/SOURCES.txt
derrick.egg-info/dependency_links.txt
derrick.egg-info/requires.txt
derrick.egg-info/top_level.txt
twisted/plugins/derrick_plugin.py