Metadata-Version: 1.0
Name: derrick
Version: 0.1.1
Summary: An ImpactJS development server.
Home-page: https://github.com/rockstar/derrick
Author: Paul Hummer
Author-email: paul@eventuallyanyway.com
License: http://www.opensource.org/licenses/mit-license.php
Keywords: impactjs html5 games
Platform: UNKNOWN
